<PurchaseOrder xmlns:xsi="http://www.w3.org/2001/XMLSchema-instance" xsi:noNamespaceSchemaLocation="http://localhost:8080/source/schemas/poSource/xsd/purchaseOrder.xsd">
   <Reference>HBAER-20100226153627967PST</Reference>
   <Actions>
      <Action>
         <User>SHIGGINS</User>
      </Action>
   </Actions>
   <Rejection/>
   <Requestor>Hermann Baer</Requestor>
   <User>HBAER</User>
   <CostCenter>A70</CostCenter>
   <ShippingInstructions>
      <name>Hermann Baer</name>
      <address>Schwanthalerstr. 7031,
Munich,
Bavaria 80925
Germany</address>
      <telephone>676-548-6214</telephone>
   </ShippingInstructions>
   <SpecialInstructions>Ground</SpecialInstructions>
   <LineItems>
      <LineItem ItemNumber="1">
         <Part Description="Benny Hill: Golden Greats" UnitPrice="27.95">26359924521</Part>
         <Quantity>8.0</Quantity>
      </LineItem>
      <LineItem ItemNumber="2">
         <Part Description="The Three Musketeers" UnitPrice="19.95">717951003201</Part>
         <Quantity>9.0</Quantity>
      </LineItem>
      <LineItem ItemNumber="3">
         <Part Description="Strike Force" UnitPrice="19.95">56775037994</Part>
         <Quantity>1.0</Quantity>
      </LineItem>
   </LineItems>
</PurchaseOrder>

