<PurchaseOrder xmlns:xsi="http://www.w3.org/2001/XMLSchema-instance" xsi:noNamespaceSchemaLocation="http://localhost:8080/source/schemas/poSource/xsd/purchaseOrder.xsd">
   <Reference>CVISHNEY-20100817202550232PDT</Reference>
   <Actions>
      <Action>
         <User>ABANDA</User>
      </Action>
   </Actions>
   <Rejection/>
   <Requestor>Clara Vishney</Requestor>
   <User>CVISHNEY</User>
   <CostCenter>A80</CostCenter>
   <ShippingInstructions>
      <name>Clara Vishney</name>
      <address>Magdalen Centre, The Oxford Science Park,
Oxford,
Oxford OX9 9ZB
United Kingdom</address>
      <telephone>888-955-1582</telephone>
   </ShippingInstructions>
   <SpecialInstructions>Next Day Air</SpecialInstructions>
   <LineItems>
      <LineItem ItemNumber="1">
         <Part Description="Dvorak: Symphony 9 In E Minor Op. 95- From The New World" UnitPrice="19.95">74644842197</Part>
         <Quantity>9.0</Quantity>
      </LineItem>
      <LineItem ItemNumber="2">
         <Part Description="Moonlighting" UnitPrice="19.95">13131099898</Part>
         <Quantity>6.0</Quantity>
      </LineItem>
      <LineItem ItemNumber="3">
         <Part Description="The Goodbye Girl" UnitPrice="19.95">12569504820</Part>
         <Quantity>7.0</Quantity>
      </LineItem>
      <LineItem ItemNumber="4">
         <Part Description="The Naked Gun: From the Files of Police Squad!" UnitPrice="27.95">97363210047</Part>
         <Quantity>8.0</Quantity>
      </LineItem>
      <LineItem ItemNumber="5">
         <Part Description="The Seventh Sign" UnitPrice="19.95">43396700796</Part>
         <Quantity>5.0</Quantity>
      </LineItem>
      <LineItem ItemNumber="6">
         <Part Description="Cherry Falls / Terror Tract" UnitPrice="19.95">696306018520</Part>
         <Quantity>4.0</Quantity>
      </LineItem>
      <LineItem ItemNumber="7">
         <Part Description="Nazca: Betrayal of Humanity" UnitPrice="19.95">13023026094</Part>
         <Quantity>8.0</Quantity>
      </LineItem>
   </LineItems>
</PurchaseOrder>

