<PurchaseOrder xmlns:xsi="http://www.w3.org/2001/XMLSchema-instance" xsi:noNamespaceSchemaLocation="http://localhost:8080/source/schemas/poSource/xsd/purchaseOrder.xsd">
   <Reference>SSEWALL-20100824204330125PDT</Reference>
   <Actions>
      <Action>
         <User>SSEWALL</User>
      </Action>
   </Actions>
   <Rejection/>
   <Requestor>Sarath Sewall</Requestor>
   <User>SSEWALL</User>
   <CostCenter>A80</CostCenter>
   <ShippingInstructions>
      <name>Sarath Sewall</name>
      <address>Magdalen Centre, The Oxford Science Park,
Oxford,
Oxford OX9 9ZB
United Kingdom</address>
      <telephone>876-477-2486</telephone>
   </ShippingInstructions>
   <SpecialInstructions>Counter to Counter</SpecialInstructions>
   <LineItems>
      <LineItem ItemNumber="1">
         <Part Description="Volunteers" UnitPrice="27.95">26359298325</Part>
         <Quantity>1.0</Quantity>
      </LineItem>
      <LineItem ItemNumber="2">
         <Part Description="Road Trip" UnitPrice="26.95">667068711127</Part>
         <Quantity>2.0</Quantity>
      </LineItem>
      <LineItem ItemNumber="3">
         <Part Description="MTV Grind Workout: Tai-Funk Aerobics" UnitPrice="19.95">74645172699</Part>
         <Quantity>1.0</Quantity>
      </LineItem>
   </LineItems>
</PurchaseOrder>

