<PurchaseOrder xmlns:xsi="http://www.w3.org/2001/XMLSchema-instance" xsi:noNamespaceSchemaLocation="http://localhost:8080/source/schemas/poSource/xsd/purchaseOrder.xsd">
   <Reference>TFOX-20100823172006801PDT</Reference>
   <Actions>
      <Action>
         <User>SKUMAR</User>
      </Action>
   </Actions>
   <Rejection/>
   <Requestor>Tayler Fox</Requestor>
   <User>TFOX</User>
   <CostCenter>A80</CostCenter>
   <ShippingInstructions>
      <name>Tayler Fox</name>
      <address>Magdalen Centre, The Oxford Science Park,
Oxford,
Oxford OX9 9ZB
United Kingdom</address>
      <telephone>343-716-5165</telephone>
   </ShippingInstructions>
   <SpecialInstructions>COD</SpecialInstructions>
   <LineItems>
      <LineItem ItemNumber="1">
         <Part Description="Bad Moon" UnitPrice="19.95">85391491026</Part>
         <Quantity>3.0</Quantity>
      </LineItem>
      <LineItem ItemNumber="2">
         <Part Description="Dirty Pictures" UnitPrice="19.95">27616851130</Part>
         <Quantity>4.0</Quantity>
      </LineItem>
      <LineItem ItemNumber="3">
         <Part Description="MVP: Most Valulable Primate" UnitPrice="19.95">85393730826</Part>
         <Quantity>5.0</Quantity>
      </LineItem>
      <LineItem ItemNumber="4">
         <Part Description="UFO and Paranormal Phenomena: Message From Another Dimension" UnitPrice="19.95">56775003890</Part>
         <Quantity>2.0</Quantity>
      </LineItem>
      <LineItem ItemNumber="5">
         <Part Description="Chocolat" UnitPrice="19.95">786936145076</Part>
         <Quantity>6.0</Quantity>
      </LineItem>
      <LineItem ItemNumber="6">
         <Part Description="Lucy Show 1" UnitPrice="27.95">56775029197</Part>
         <Quantity>4.0</Quantity>
      </LineItem>
   </LineItems>
</PurchaseOrder>

