<PurchaseOrder xmlns:xsi="http://www.w3.org/2001/XMLSchema-instance" xsi:noNamespaceSchemaLocation="http://localhost:8080/source/schemas/poSource/xsd/purchaseOrder.xsd">
   <Reference>CJOHNSON-20100918225756565PDT</Reference>
   <Actions>
      <Action>
         <User>CJOHNSON</User>
      </Action>
   </Actions>
   <Rejection/>
   <Requestor>Charles Johnson</Requestor>
   <User>CJOHNSON</User>
   <CostCenter>A80</CostCenter>
   <ShippingInstructions>
      <name>Charles Johnson</name>
      <address>Magdalen Centre, The Oxford Science Park,
Oxford,
Oxford OX9 9ZB
United Kingdom</address>
      <telephone>611-922-3292</telephone>
   </ShippingInstructions>
   <SpecialInstructions>Expidite</SpecialInstructions>
   <LineItems>
      <LineItem ItemNumber="1">
         <Part Description="Leaving Las Vegas" UnitPrice="19.95">27616699725</Part>
         <Quantity>5.0</Quantity>
      </LineItem>
      <LineItem ItemNumber="2">
         <Part Description="Dragon Ball Z: Androids- Dr Gero" UnitPrice="0.0">704400030055</Part>
         <Quantity>8.0</Quantity>
      </LineItem>
      <LineItem ItemNumber="3">
         <Part Description="Star Trek 19: Changeling / Apple" UnitPrice="19.95">97366001949</Part>
         <Quantity>8.0</Quantity>
      </LineItem>
      <LineItem ItemNumber="4">
         <Part Description="Psycho III" UnitPrice="19.95">18713810458</Part>
         <Quantity>1.0</Quantity>
      </LineItem>
      <LineItem ItemNumber="5">
         <Part Description="Pokemon: Into The Arena" UnitPrice="19.95">13023048690</Part>
         <Quantity>1.0</Quantity>
      </LineItem>
   </LineItems>
</PurchaseOrder>

