<PurchaseOrder xmlns:xsi="http://www.w3.org/2001/XMLSchema-instance" xsi:noNamespaceSchemaLocation="http://localhost:8080/source/schemas/poSource/xsd/purchaseOrder.xsd">
   <Reference>PKAUFLIN-20100912172249907PDT</Reference>
   <Actions>
      <Action>
         <User>MHARTSTE</User>
      </Action>
   </Actions>
   <Rejection/>
   <Requestor>Payam Kaufling</Requestor>
   <User>PKAUFLIN</User>
   <CostCenter>A50</CostCenter>
   <ShippingInstructions>
      <name>Payam Kaufling</name>
      <address>2011 Interiors Blvd,
South San Francisco,
California 99236
United States of America</address>
      <telephone>891-278-4551</telephone>
   </ShippingInstructions>
   <SpecialInstructions>Priority Overnight</SpecialInstructions>
   <LineItems>
      <LineItem ItemNumber="1">
         <Part Description="Everest" UnitPrice="19.95">717951001658</Part>
         <Quantity>4.0</Quantity>
      </LineItem>
      <LineItem ItemNumber="2">
         <Part Description="Hoods" UnitPrice="19.95">13023032897</Part>
         <Quantity>2.0</Quantity>
      </LineItem>
      <LineItem ItemNumber="3">
         <Part Description="Saturn 3" UnitPrice="19.95">13023029293</Part>
         <Quantity>1.0</Quantity>
      </LineItem>
      <LineItem ItemNumber="4">
         <Part Description="The Standard Deviants: English Composition" UnitPrice="27.95">631865003426</Part>
         <Quantity>7.0</Quantity>
      </LineItem>
   </LineItems>
</PurchaseOrder>

