<PurchaseOrder xmlns:xsi="http://www.w3.org/2001/XMLSchema-instance" xsi:noNamespaceSchemaLocation="http://localhost:8080/source/schemas/poSource/xsd/purchaseOrder.xsd">
   <Reference>STOBIAS-20100404211825668PDT</Reference>
   <Actions>
      <Action>
         <User>KCOLMENA</User>
      </Action>
   </Actions>
   <Rejection/>
   <Requestor>Sigal Tobias</Requestor>
   <User>STOBIAS</User>
   <CostCenter>A30</CostCenter>
   <ShippingInstructions>
      <name>Sigal Tobias</name>
      <address>2004 Charade Rd,
Seattle,
Washington 98199
United States of America</address>
      <telephone>423-461-4233</telephone>
   </ShippingInstructions>
   <SpecialInstructions>Priority Overnight</SpecialInstructions>
   <LineItems>
      <LineItem ItemNumber="1">
         <Part Description="La Cucaracha" UnitPrice="19.95">97368397545</Part>
         <Quantity>6.0</Quantity>
      </LineItem>
      <LineItem ItemNumber="2">
         <Part Description="Pinocchio" UnitPrice="19.95">717951005793</Part>
         <Quantity>7.0</Quantity>
      </LineItem>
      <LineItem ItemNumber="3">
         <Part Description="Panther" UnitPrice="19.95">780063630924</Part>
         <Quantity>6.0</Quantity>
      </LineItem>
      <LineItem ItemNumber="4">
         <Part Description="Karaoke: The Gentlemen of Country Vol.2 202" UnitPrice="19.95">13023003392</Part>
         <Quantity>4.0</Quantity>
      </LineItem>
   </LineItems>
</PurchaseOrder>

