<PurchaseOrder xmlns:xsi="http://www.w3.org/2001/XMLSchema-instance" xsi:noNamespaceSchemaLocation="http://localhost:8080/source/schemas/poSource/xsd/purchaseOrder.xsd">
   <Reference>WTAYLOR-20100412130311603PDT</Reference>
   <Actions>
      <Action>
         <User>GGEONI</User>
      </Action>
   </Actions>
   <Rejection/>
   <Requestor>Winston Taylor</Requestor>
   <User>WTAYLOR</User>
   <CostCenter>A50</CostCenter>
   <ShippingInstructions>
      <name>Winston Taylor</name>
      <address>2011 Interiors Blvd,
South San Francisco,
California 99236
United States of America</address>
      <telephone>926-179-8296</telephone>
   </ShippingInstructions>
   <SpecialInstructions>Surface Mail</SpecialInstructions>
   <LineItems>
      <LineItem ItemNumber="1">
         <Part Description="The 7th Voyage of Sinbad" UnitPrice="19.95">43396011496</Part>
         <Quantity>6.0</Quantity>
      </LineItem>
      <LineItem ItemNumber="2">
         <Part Description="Superman II" UnitPrice="19.95">85391112020</Part>
         <Quantity>1.0</Quantity>
      </LineItem>
      <LineItem ItemNumber="3">
         <Part Description="Coyote Ugly &amp; Pretty Woman 10th Anniv" UnitPrice="32.95">786936161274</Part>
         <Quantity>7.0</Quantity>
      </LineItem>
      <LineItem ItemNumber="4">
         <Part Description="Blue Steel &amp; Hell Town" UnitPrice="19.95">18713811080</Part>
         <Quantity>8.0</Quantity>
      </LineItem>
      <LineItem ItemNumber="5">
         <Part Description="The Killing Hour" UnitPrice="19.95">13131107890</Part>
         <Quantity>1.0</Quantity>
      </LineItem>
   </LineItems>
</PurchaseOrder>

