<PurchaseOrder xmlns:xsi="http://www.w3.org/2001/XMLSchema-instance" xsi:noNamespaceSchemaLocation="http://localhost:8080/source/schemas/poSource/xsd/purchaseOrder.xsd">
   <Reference>LPOPP-20100601145432561PDT</Reference>
   <Actions>
      <Action>
         <User>LPOPP</User>
      </Action>
   </Actions>
   <Rejection/>
   <Requestor>Luis Popp</Requestor>
   <User>LPOPP</User>
   <CostCenter>A100</CostCenter>
   <ShippingInstructions>
      <name>Luis Popp</name>
      <address>2004 Charade Rd,
Seattle,
Washington 98199
United States of America</address>
      <telephone>532-359-5669</telephone>
   </ShippingInstructions>
   <SpecialInstructions>Counter to Counter</SpecialInstructions>
   <LineItems>
      <LineItem ItemNumber="1">
         <Part Description="Pet Sematary" UnitPrice="19.95">97360194944</Part>
         <Quantity>7.0</Quantity>
      </LineItem>
      <LineItem ItemNumber="2">
         <Part Description="Sprung" UnitPrice="19.95">31398688433</Part>
         <Quantity>7.0</Quantity>
      </LineItem>
      <LineItem ItemNumber="3">
         <Part Description="I Just Wasn't Made for These Times" UnitPrice="19.95">13023029897</Part>
         <Quantity>8.0</Quantity>
      </LineItem>
      <LineItem ItemNumber="4">
         <Part Description="Central Station" UnitPrice="19.95">43396038332</Part>
         <Quantity>7.0</Quantity>
      </LineItem>
      <LineItem ItemNumber="5">
         <Part Description="Restraining Order" UnitPrice="19.95">12236106340</Part>
         <Quantity>3.0</Quantity>
      </LineItem>
   </LineItems>
</PurchaseOrder>

