<PurchaseOrder xmlns:xsi="http://www.w3.org/2001/XMLSchema-instance" xsi:noNamespaceSchemaLocation="http://localhost:8080/source/schemas/poSource/xsd/purchaseOrder.xsd">
   <Reference>BERNST-20101115121233295PST</Reference>
   <Actions>
      <Action>
         <User>DLORENTZ</User>
      </Action>
   </Actions>
   <Rejection/>
   <Requestor>Bruce Ernst</Requestor>
   <User>BERNST</User>
   <CostCenter>A60</CostCenter>
   <ShippingInstructions>
      <name>Bruce Ernst</name>
      <address>2014 Jabberwocky Rd,
Southlake,
Texas 26192
United States of America</address>
      <telephone>389-989-5149</telephone>
   </ShippingInstructions>
   <SpecialInstructions>COD</SpecialInstructions>
   <LineItems>
      <LineItem ItemNumber="1">
         <Part Description="What Ever Happened to Baby Jane?" UnitPrice="19.95">85391105121</Part>
         <Quantity>6.0</Quantity>
      </LineItem>
      <LineItem ItemNumber="2">
         <Part Description="Heaven's Gate" UnitPrice="19.95">27616837127</Part>
         <Quantity>6.0</Quantity>
      </LineItem>
      <LineItem ItemNumber="3">
         <Part Description="Thirty Two Short Films About Glenn Gould" UnitPrice="27.95">43396743595</Part>
         <Quantity>5.0</Quantity>
      </LineItem>
      <LineItem ItemNumber="4">
         <Part Description="Sailor Moon S: Heart Collection 2" UnitPrice="19.95">13023147591</Part>
         <Quantity>1.0</Quantity>
      </LineItem>
      <LineItem ItemNumber="5">
         <Part Description="Classical Visions: Beethoven- Spring Flowers" UnitPrice="19.95">56775016692</Part>
         <Quantity>4.0</Quantity>
      </LineItem>
      <LineItem ItemNumber="6">
         <Part Description="Bucktown" UnitPrice="19.95">27616867810</Part>
         <Quantity>1.0</Quantity>
      </LineItem>
   </LineItems>
</PurchaseOrder>

