<PurchaseOrder xmlns:xsi="http://www.w3.org/2001/XMLSchema-instance" xsi:noNamespaceSchemaLocation="http://localhost:8080/source/schemas/poSource/xsd/purchaseOrder.xsd">
   <Reference>CDAVIES-20101116180726658PST</Reference>
   <Actions>
      <Action>
         <User>DGRANT</User>
      </Action>
   </Actions>
   <Rejection/>
   <Requestor>Curtis Davies</Requestor>
   <User>CDAVIES</User>
   <CostCenter>A50</CostCenter>
   <ShippingInstructions>
      <name>Curtis Davies</name>
      <address>2011 Interiors Blvd,
South San Francisco,
California 99236
United States of America</address>
      <telephone>474-428-8130</telephone>
   </ShippingInstructions>
   <SpecialInstructions>Next Day Air</SpecialInstructions>
   <LineItems>
      <LineItem ItemNumber="1">
         <Part Description="Nico The Unicorn / Owd Bob" UnitPrice="19.95">696306029021</Part>
         <Quantity>7.0</Quantity>
      </LineItem>
      <LineItem ItemNumber="2">
         <Part Description="Bunin: Chopin and Debussy" UnitPrice="19.95">13023028098</Part>
         <Quantity>4.0</Quantity>
      </LineItem>
      <LineItem ItemNumber="3">
         <Part Description="Skeletons in the Closet" UnitPrice="19.95">12236119371</Part>
         <Quantity>7.0</Quantity>
      </LineItem>
   </LineItems>
</PurchaseOrder>

