<PurchaseOrder xmlns:xsi="http://www.w3.org/2001/XMLSchema-instance" xsi:noNamespaceSchemaLocation="http://localhost:8080/source/schemas/poSource/xsd/purchaseOrder.xsd">
   <Reference>KCOLMENA-20101105145604779PST</Reference>
   <Actions>
      <Action>
         <User>KCOLMENA</User>
      </Action>
   </Actions>
   <Rejection/>
   <Requestor>Karen Colmenares</Requestor>
   <User>KCOLMENA</User>
   <CostCenter>A30</CostCenter>
   <ShippingInstructions>
      <name>Karen Colmenares</name>
      <address>2004 Charade Rd,
Seattle,
Washington 98199
United States of America</address>
      <telephone>959-349-1830</telephone>
   </ShippingInstructions>
   <SpecialInstructions>Air Mail</SpecialInstructions>
   <LineItems>
      <LineItem ItemNumber="1">
         <Part Description="Elizabeth Taylor" UnitPrice="19.95">56775036799</Part>
         <Quantity>9.0</Quantity>
      </LineItem>
      <LineItem ItemNumber="2">
         <Part Description="Dario Argento Gift Set 3: Deep Red / Tenebre" UnitPrice="27.95">13131170498</Part>
         <Quantity>2.0</Quantity>
      </LineItem>
      <LineItem ItemNumber="3">
         <Part Description="Dragon Tales: Fury is Out on This One" UnitPrice="19.95">43396046115</Part>
         <Quantity>8.0</Quantity>
      </LineItem>
   </LineItems>
</PurchaseOrder>

