<PurchaseOrder xmlns:xsi="http://www.w3.org/2001/XMLSchema-instance" xsi:noNamespaceSchemaLocation="http://localhost:8080/source/schemas/poSource/xsd/purchaseOrder.xsd">
   <Reference>MSULLIVA-20101113193634737PST</Reference>
   <Actions>
      <Action>
         <User>GGEONI</User>
      </Action>
   </Actions>
   <Rejection/>
   <Requestor>Martha Sullivan</Requestor>
   <User>MSULLIVA</User>
   <CostCenter>A50</CostCenter>
   <ShippingInstructions>
      <name>Martha Sullivan</name>
      <address>2011 Interiors Blvd,
South San Francisco,
California 99236
United States of America</address>
      <telephone>716-616-2648</telephone>
   </ShippingInstructions>
   <SpecialInstructions>Next Day Air</SpecialInstructions>
   <LineItems>
      <LineItem ItemNumber="1">
         <Part Description="Menace II Society" UnitPrice="19.95">794043416521</Part>
         <Quantity>3.0</Quantity>
      </LineItem>
      <LineItem ItemNumber="2">
         <Part Description="Best of Musikladen Live: Procol Harum" UnitPrice="19.95">13023027862</Part>
         <Quantity>5.0</Quantity>
      </LineItem>
      <LineItem ItemNumber="3">
         <Part Description="Anywhere But Here" UnitPrice="27.95">24543000365</Part>
         <Quantity>9.0</Quantity>
      </LineItem>
      <LineItem ItemNumber="4">
         <Part Description="Stardom" UnitPrice="27.95">25192126024</Part>
         <Quantity>8.0</Quantity>
      </LineItem>
      <LineItem ItemNumber="5">
         <Part Description="The Hollywood Knights" UnitPrice="19.95">43396218949</Part>
         <Quantity>9.0</Quantity>
      </LineItem>
   </LineItems>
</PurchaseOrder>

