<PurchaseOrder xmlns:xsi="http://www.w3.org/2001/XMLSchema-instance" xsi:noNamespaceSchemaLocation="http://localhost:8080/source/schemas/poSource/xsd/purchaseOrder.xsd">
   <Reference>AWALSH-20100115213811839PST</Reference>
   <Actions>
      <Action>
         <User>DGRANT</User>
      </Action>
   </Actions>
   <Rejection/>
   <Requestor>Alana Walsh</Requestor>
   <User>AWALSH</User>
   <CostCenter>A50</CostCenter>
   <ShippingInstructions>
      <name>Alana Walsh</name>
      <address>2011 Interiors Blvd,
South San Francisco,
California 99236
United States of America</address>
      <telephone>638-523-8341</telephone>
   </ShippingInstructions>
   <SpecialInstructions>Courier</SpecialInstructions>
   <LineItems>
      <LineItem ItemNumber="1">
         <Part Description="Herbert Von Karajan- His Legacy for Home Video: Beethoven- Concerto in D Major For Violin &amp; Orchest" UnitPrice="19.95">74644638592</Part>
         <Quantity>6.0</Quantity>
      </LineItem>
      <LineItem ItemNumber="2">
         <Part Description="The Hobbit" UnitPrice="19.95">12569056626</Part>
         <Quantity>5.0</Quantity>
      </LineItem>
      <LineItem ItemNumber="3">
         <Part Description="Scorpio" UnitPrice="19.95">27616799821</Part>
         <Quantity>7.0</Quantity>
      </LineItem>
      <LineItem ItemNumber="4">
         <Part Description="Some Mothers Do 'Ave 'Em!: Have Break" UnitPrice="19.95">66805301513</Part>
         <Quantity>5.0</Quantity>
      </LineItem>
      <LineItem ItemNumber="5">
         <Part Description="Whitney Houston: Fine/If I Told You That/I Will Always Love You" UnitPrice="19.95">78221392099</Part>
         <Quantity>6.0</Quantity>
      </LineItem>
      <LineItem ItemNumber="6">
         <Part Description="Hercules: Warrior Princess / Gauntlet" UnitPrice="19.95">25192025624</Part>
         <Quantity>7.0</Quantity>
      </LineItem>
   </LineItems>
</PurchaseOrder>

