<PurchaseOrder xmlns:xsi="http://www.w3.org/2001/XMLSchema-instance" xsi:noNamespaceSchemaLocation="http://localhost:8080/source/schemas/poSource/xsd/purchaseOrder.xsd">
   <Reference>KCOLMENA-20100116153525313PST</Reference>
   <Actions>
      <Action>
         <User>KCOLMENA</User>
      </Action>
   </Actions>
   <Rejection/>
   <Requestor>Karen Colmenares</Requestor>
   <User>KCOLMENA</User>
   <CostCenter>A30</CostCenter>
   <ShippingInstructions>
      <name>Karen Colmenares</name>
      <address>2004 Charade Rd,
Seattle,
Washington 98199
United States of America</address>
      <telephone>251-295-9015</telephone>
   </ShippingInstructions>
   <SpecialInstructions>Hand Carry</SpecialInstructions>
   <LineItems>
      <LineItem ItemNumber="1">
         <Part Description="Nightmares" UnitPrice="19.95">13131086997</Part>
         <Quantity>3.0</Quantity>
      </LineItem>
      <LineItem ItemNumber="2">
         <Part Description="Patrouille De France" UnitPrice="19.95">13023016798</Part>
         <Quantity>6.0</Quantity>
      </LineItem>
      <LineItem ItemNumber="3">
         <Part Description="Hansel and Gretel" UnitPrice="19.95">13023144996</Part>
         <Quantity>1.0</Quantity>
      </LineItem>
      <LineItem ItemNumber="4">
         <Part Description="Bringing Out the Dead" UnitPrice="19.95">97363356448</Part>
         <Quantity>2.0</Quantity>
      </LineItem>
      <LineItem ItemNumber="5">
         <Part Description="Ruffhouse 10th Anniversary Greatest Hits" UnitPrice="19.95">74645019697</Part>
         <Quantity>8.0</Quantity>
      </LineItem>
   </LineItems>
</PurchaseOrder>

