<PurchaseOrder xmlns:xsi="http://www.w3.org/2001/XMLSchema-instance" xsi:noNamespaceSchemaLocation="http://localhost:8080/source/schemas/poSource/xsd/purchaseOrder.xsd">
   <Reference>TRAJS-20100116195028801PST</Reference>
   <Actions>
      <Action>
         <User>DGRANT</User>
      </Action>
   </Actions>
   <Rejection/>
   <Requestor>Trenna Rajs</Requestor>
   <User>TRAJS</User>
   <CostCenter>A50</CostCenter>
   <ShippingInstructions>
      <name>Trenna Rajs</name>
      <address>2011 Interiors Blvd,
South San Francisco,
California 99236
United States of America</address>
      <telephone>851-47-1938</telephone>
   </ShippingInstructions>
   <SpecialInstructions>Courier</SpecialInstructions>
   <LineItems>
      <LineItem ItemNumber="1">
         <Part Description="StrangeLand" UnitPrice="19.95">12236049807</Part>
         <Quantity>9.0</Quantity>
      </LineItem>
      <LineItem ItemNumber="2">
         <Part Description="The Nuttiest Nutcracker" UnitPrice="19.95">43396251892</Part>
         <Quantity>4.0</Quantity>
      </LineItem>
      <LineItem ItemNumber="3">
         <Part Description="Black Sabbath: The Last Supper" UnitPrice="19.95">74645018799</Part>
         <Quantity>9.0</Quantity>
      </LineItem>
      <LineItem ItemNumber="4">
         <Part Description="Warriors of Virtue" UnitPrice="19.95">27616743428</Part>
         <Quantity>3.0</Quantity>
      </LineItem>
      <LineItem ItemNumber="5">
         <Part Description="Blue Velvet" UnitPrice="19.95">27616805928</Part>
         <Quantity>9.0</Quantity>
      </LineItem>
   </LineItems>
</PurchaseOrder>

