<PurchaseOrder xmlns:xsi="http://www.w3.org/2001/XMLSchema-instance" xsi:noNamespaceSchemaLocation="http://localhost:8080/source/schemas/poSource/xsd/purchaseOrder.xsd">
   <Reference>AMCEWEN-20100510214526479PDT</Reference>
   <Actions>
      <Action>
         <User>SSEWALL</User>
      </Action>
   </Actions>
   <Rejection/>
   <Requestor>Allan McEwen</Requestor>
   <User>AMCEWEN</User>
   <CostCenter>A80</CostCenter>
   <ShippingInstructions>
      <name>Allan McEwen</name>
      <address>Magdalen Centre, The Oxford Science Park,
Oxford,
Oxford OX9 9ZB
United Kingdom</address>
      <telephone>340-172-7856</telephone>
   </ShippingInstructions>
   <SpecialInstructions>Air Mail</SpecialInstructions>
   <LineItems>
      <LineItem ItemNumber="1">
         <Part Description="Up Close &amp; Personal" UnitPrice="19.95">717951003447</Part>
         <Quantity>8.0</Quantity>
      </LineItem>
      <LineItem ItemNumber="2">
         <Part Description="Father Ted: Complete Series 1" UnitPrice="27.95">794051156426</Part>
         <Quantity>1.0</Quantity>
      </LineItem>
      <LineItem ItemNumber="3">
         <Part Description="Saturn 3" UnitPrice="19.95">13023029293</Part>
         <Quantity>8.0</Quantity>
      </LineItem>
      <LineItem ItemNumber="4">
         <Part Description="Charlotte's Web" UnitPrice="27.95">97361564548</Part>
         <Quantity>4.0</Quantity>
      </LineItem>
      <LineItem ItemNumber="5">
         <Part Description="Marnie" UnitPrice="19.95">25192058721</Part>
         <Quantity>1.0</Quantity>
      </LineItem>
      <LineItem ItemNumber="6">
         <Part Description="Double Impact" UnitPrice="19.95">27616858627</Part>
         <Quantity>6.0</Quantity>
      </LineItem>
   </LineItems>
</PurchaseOrder>

