<PurchaseOrder xmlns:xsi="http://www.w3.org/2001/XMLSchema-instance" xsi:noNamespaceSchemaLocation="http://localhost:8080/source/schemas/poSource/xsd/purchaseOrder.xsd">
   <Reference>OTUVAULT-20100527160319950PDT</Reference>
   <Actions>
      <Action>
         <User>OTUVAULT</User>
      </Action>
   </Actions>
   <Rejection/>
   <Requestor>Oliver Tuvault</Requestor>
   <User>OTUVAULT</User>
   <CostCenter>A80</CostCenter>
   <ShippingInstructions>
      <name>Oliver Tuvault</name>
      <address>Magdalen Centre, The Oxford Science Park,
Oxford,
Oxford OX9 9ZB
United Kingdom</address>
      <telephone>791-233-2196</telephone>
   </ShippingInstructions>
   <SpecialInstructions>Priority Overnight</SpecialInstructions>
   <LineItems>
      <LineItem ItemNumber="1">
         <Part Description="The Art Of War" UnitPrice="19.95">85391887126</Part>
         <Quantity>3.0</Quantity>
      </LineItem>
      <LineItem ItemNumber="2">
         <Part Description="Shake, Rattle &amp; Rock!" UnitPrice="27.95">786936159943</Part>
         <Quantity>7.0</Quantity>
      </LineItem>
      <LineItem ItemNumber="3">
         <Part Description="The King of Marvin Gardens" UnitPrice="19.95">43396528093</Part>
         <Quantity>5.0</Quantity>
      </LineItem>
      <LineItem ItemNumber="4">
         <Part Description="Chariots of Fire" UnitPrice="19.95">85392000425</Part>
         <Quantity>5.0</Quantity>
      </LineItem>
   </LineItems>
</PurchaseOrder>

