<PurchaseOrder xmlns:xsi="http://www.w3.org/2001/XMLSchema-instance" xsi:noNamespaceSchemaLocation="http://localhost:8080/source/schemas/poSource/xsd/purchaseOrder.xsd">
   <Reference>PSULLY-20100509215648899PDT</Reference>
   <Actions>
      <Action>
         <User>SSEWALL</User>
      </Action>
   </Actions>
   <Rejection/>
   <Requestor>Patrick Sully</Requestor>
   <User>PSULLY</User>
   <CostCenter>A80</CostCenter>
   <ShippingInstructions>
      <name>Patrick Sully</name>
      <address>Magdalen Centre, The Oxford Science Park,
Oxford,
Oxford OX9 9ZB
United Kingdom</address>
      <telephone>509-126-1978</telephone>
   </ShippingInstructions>
   <SpecialInstructions>Surface Mail</SpecialInstructions>
   <LineItems>
      <LineItem ItemNumber="1">
         <Part Description="Nutty Professor II: The Klumps" UnitPrice="19.95">25192092220</Part>
         <Quantity>2.0</Quantity>
      </LineItem>
      <LineItem ItemNumber="2">
         <Part Description="Agent Red" UnitPrice="19.95">43396064829</Part>
         <Quantity>7.0</Quantity>
      </LineItem>
      <LineItem ItemNumber="3">
         <Part Description="The Pirates of Penzance" UnitPrice="29.95">54961348091</Part>
         <Quantity>3.0</Quantity>
      </LineItem>
      <LineItem ItemNumber="4">
         <Part Description="The Lair of the White Worm" UnitPrice="19.95">13023011298</Part>
         <Quantity>3.0</Quantity>
      </LineItem>
      <LineItem ItemNumber="5">
         <Part Description="Not without My Daughter" UnitPrice="19.95">27616867773</Part>
         <Quantity>7.0</Quantity>
      </LineItem>
   </LineItems>
</PurchaseOrder>

