<PurchaseOrder xmlns:xsi="http://www.w3.org/2001/XMLSchema-instance" xsi:noNamespaceSchemaLocation="http://localhost:8080/source/schemas/poSource/xsd/purchaseOrder.xsd">
   <Reference>RLADWIG-20100510220225487PDT</Reference>
   <Actions>
      <Action>
         <User>VJONES</User>
      </Action>
   </Actions>
   <Rejection/>
   <Requestor>Renske Ladwig</Requestor>
   <User>RLADWIG</User>
   <CostCenter>A50</CostCenter>
   <ShippingInstructions>
      <name>Renske Ladwig</name>
      <address>2011 Interiors Blvd,
South San Francisco,
California 99236
United States of America</address>
      <telephone>780-849-2010</telephone>
   </ShippingInstructions>
   <SpecialInstructions>Courier</SpecialInstructions>
   <LineItems>
      <LineItem ItemNumber="1">
         <Part Description="Ice Castles" UnitPrice="27.95">43396062023</Part>
         <Quantity>6.0</Quantity>
      </LineItem>
      <LineItem ItemNumber="2">
         <Part Description="Buzz Lightyear of Star Command: The Adventure -- begins" UnitPrice="19.95">717951008404</Part>
         <Quantity>7.0</Quantity>
      </LineItem>
      <LineItem ItemNumber="3">
         <Part Description="Earthquake" UnitPrice="19.95">18713810274</Part>
         <Quantity>1.0</Quantity>
      </LineItem>
   </LineItems>
</PurchaseOrder>

