<PurchaseOrder xmlns:xsi="http://www.w3.org/2001/XMLSchema-instance" xsi:noNamespaceSchemaLocation="http://localhost:8080/source/schemas/poSource/xsd/purchaseOrder.xsd">
   <Reference>COLSEN-20101027135442862PDT</Reference>
   <Actions>
      <Action>
         <User>OTUVAULT</User>
      </Action>
   </Actions>
   <Rejection/>
   <Requestor>Christopher Olsen</Requestor>
   <User>COLSEN</User>
   <CostCenter>A80</CostCenter>
   <ShippingInstructions>
      <name>Christopher Olsen</name>
      <address>Magdalen Centre, The Oxford Science Park,
Oxford,
Oxford OX9 9ZB
United Kingdom</address>
      <telephone>840-641-7679</telephone>
   </ShippingInstructions>
   <SpecialInstructions>Surface Mail</SpecialInstructions>
   <LineItems>
      <LineItem ItemNumber="1">
         <Part Description="In the Presence of Mine Enemies" UnitPrice="19.95">13023152298</Part>
         <Quantity>4.0</Quantity>
      </LineItem>
      <LineItem ItemNumber="2">
         <Part Description="Liar Liar / EdTV" UnitPrice="19.95">25192141522</Part>
         <Quantity>3.0</Quantity>
      </LineItem>
      <LineItem ItemNumber="3">
         <Part Description="The Bear" UnitPrice="19.95">43396039940</Part>
         <Quantity>9.0</Quantity>
      </LineItem>
      <LineItem ItemNumber="4">
         <Part Description="Pokemon: Round One" UnitPrice="19.95">13023048799</Part>
         <Quantity>9.0</Quantity>
      </LineItem>
      <LineItem ItemNumber="5">
         <Part Description="Queensryche: Live Evolution" UnitPrice="27.95">60768831698</Part>
         <Quantity>6.0</Quantity>
      </LineItem>
   </LineItems>
</PurchaseOrder>

