<PurchaseOrder xmlns:xsi="http://www.w3.org/2001/XMLSchema-instance" xsi:noNamespaceSchemaLocation="http://localhost:8080/source/schemas/poSource/xsd/purchaseOrder.xsd">
   <Reference>DBERNSTE-20101023210011608PDT</Reference>
   <Actions>
      <Action>
         <User>OTUVAULT</User>
      </Action>
   </Actions>
   <Rejection/>
   <Requestor>David Bernstein</Requestor>
   <User>DBERNSTE</User>
   <CostCenter>A80</CostCenter>
   <ShippingInstructions>
      <name>David Bernstein</name>
      <address>Magdalen Centre, The Oxford Science Park,
Oxford,
Oxford OX9 9ZB
United Kingdom</address>
      <telephone>928-842-9018</telephone>
   </ShippingInstructions>
   <SpecialInstructions>Ground</SpecialInstructions>
   <LineItems>
      <LineItem ItemNumber="1">
         <Part Description="Threesome" UnitPrice="19.95">43396058569</Part>
         <Quantity>9.0</Quantity>
      </LineItem>
      <LineItem ItemNumber="2">
         <Part Description="Solo" UnitPrice="19.95">43396825895</Part>
         <Quantity>7.0</Quantity>
      </LineItem>
      <LineItem ItemNumber="3">
         <Part Description="Gulliver's Travels" UnitPrice="27.95">707729101864</Part>
         <Quantity>3.0</Quantity>
      </LineItem>
      <LineItem ItemNumber="4">
         <Part Description="Best of DVD" UnitPrice="19.95">31398704232</Part>
         <Quantity>6.0</Quantity>
      </LineItem>
   </LineItems>
</PurchaseOrder>

