<PurchaseOrder xmlns:xsi="http://www.w3.org/2001/XMLSchema-instance" xsi:noNamespaceSchemaLocation="http://localhost:8080/source/schemas/poSource/xsd/purchaseOrder.xsd">
   <Reference>IMIKKILI-20101223220619345PST</Reference>
   <Actions>
      <Action>
         <User>GGEONI</User>
      </Action>
   </Actions>
   <Rejection/>
   <Requestor>Irene Mikkilineni</Requestor>
   <User>IMIKKILI</User>
   <CostCenter>A50</CostCenter>
   <ShippingInstructions>
      <name>Irene Mikkilineni</name>
      <address>2011 Interiors Blvd,
South San Francisco,
California 99236
United States of America</address>
      <telephone>496-337-4205</telephone>
   </ShippingInstructions>
   <SpecialInstructions>Counter to Counter</SpecialInstructions>
   <LineItems>
      <LineItem ItemNumber="1">
         <Part Description="Abbott and Costello Meet the Mummy" UnitPrice="19.95">25192057328</Part>
         <Quantity>8.0</Quantity>
      </LineItem>
      <LineItem ItemNumber="2">
         <Part Description="Twilight Zone 31" UnitPrice="19.95">14381894820</Part>
         <Quantity>3.0</Quantity>
      </LineItem>
      <LineItem ItemNumber="3">
         <Part Description="Running on Empty" UnitPrice="19.95">85391184324</Part>
         <Quantity>3.0</Quantity>
      </LineItem>
   </LineItems>
</PurchaseOrder>

