<PurchaseOrder xmlns:xsi="http://www.w3.org/2001/XMLSchema-instance" xsi:noNamespaceSchemaLocation="http://localhost:8080/source/schemas/poSource/xsd/purchaseOrder.xsd">
   <Reference>VPATABAL-20101218180534659PST</Reference>
   <Actions>
      <Action>
         <User>DLORENTZ</User>
      </Action>
   </Actions>
   <Rejection/>
   <Requestor>Valli Pataballa</Requestor>
   <User>VPATABAL</User>
   <CostCenter>A60</CostCenter>
   <ShippingInstructions>
      <name>Valli Pataballa</name>
      <address>2014 Jabberwocky Rd,
Southlake,
Texas 26192
United States of America</address>
      <telephone>934-808-4580</telephone>
   </ShippingInstructions>
   <SpecialInstructions>Hand Carry</SpecialInstructions>
   <LineItems>
      <LineItem ItemNumber="1">
         <Part Description="Freddy Got Fingered" UnitPrice="27.95">24543024590</Part>
         <Quantity>9.0</Quantity>
      </LineItem>
      <LineItem ItemNumber="2">
         <Part Description="Snake Eyes" UnitPrice="19.95">97363354178</Part>
         <Quantity>3.0</Quantity>
      </LineItem>
      <LineItem ItemNumber="3">
         <Part Description="The Pallbearer" UnitPrice="19.95">717951003218</Part>
         <Quantity>8.0</Quantity>
      </LineItem>
      <LineItem ItemNumber="4">
         <Part Description="Message To Love" UnitPrice="19.95">74644933598</Part>
         <Quantity>3.0</Quantity>
      </LineItem>
   </LineItems>
</PurchaseOrder>

