<PurchaseOrder xmlns:xsi="http://www.w3.org/2001/XMLSchema-instance" xsi:noNamespaceSchemaLocation="http://localhost:8080/source/schemas/poSource/xsd/purchaseOrder.xsd">
   <Reference>DGREENE-20100727153422599PDT</Reference>
   <Actions>
      <Action>
         <User>ABANDA</User>
      </Action>
   </Actions>
   <Rejection/>
   <Requestor>Danielle Greene</Requestor>
   <User>DGREENE</User>
   <CostCenter>A80</CostCenter>
   <ShippingInstructions>
      <name>Danielle Greene</name>
      <address>Magdalen Centre, The Oxford Science Park,
Oxford,
Oxford OX9 9ZB
United Kingdom</address>
      <telephone>133-932-6232</telephone>
   </ShippingInstructions>
   <SpecialInstructions>Surface Mail</SpecialInstructions>
   <LineItems>
      <LineItem ItemNumber="1">
         <Part Description="Guys and Dolls" UnitPrice="19.95">27616809322</Part>
         <Quantity>8.0</Quantity>
      </LineItem>
      <LineItem ItemNumber="2">
         <Part Description="Civil Action &amp; Insider" UnitPrice="32.95">786936159509</Part>
         <Quantity>2.0</Quantity>
      </LineItem>
      <LineItem ItemNumber="3">
         <Part Description="The Munster's Revenge" UnitPrice="19.95">18713810250</Part>
         <Quantity>8.0</Quantity>
      </LineItem>
      <LineItem ItemNumber="4">
         <Part Description="School Daze" UnitPrice="27.95">43396058347</Part>
         <Quantity>4.0</Quantity>
      </LineItem>
      <LineItem ItemNumber="5">
         <Part Description="Keeping the Faith" UnitPrice="27.95">717951010582</Part>
         <Quantity>4.0</Quantity>
      </LineItem>
   </LineItems>
</PurchaseOrder>

