<PurchaseOrder xmlns:xsi="http://www.w3.org/2001/XMLSchema-instance" xsi:noNamespaceSchemaLocation="http://localhost:8080/source/schemas/poSource/xsd/purchaseOrder.xsd">
   <Reference>RLADWIG-20100716173939149PDT</Reference>
   <Actions>
      <Action>
         <User>VJONES</User>
      </Action>
   </Actions>
   <Rejection/>
   <Requestor>Renske Ladwig</Requestor>
   <User>RLADWIG</User>
   <CostCenter>A50</CostCenter>
   <ShippingInstructions>
      <name>Renske Ladwig</name>
      <address>2011 Interiors Blvd,
South San Francisco,
California 99236
United States of America</address>
      <telephone>147-316-6881</telephone>
   </ShippingInstructions>
   <SpecialInstructions>Air Mail</SpecialInstructions>
   <LineItems>
      <LineItem ItemNumber="1">
         <Part Description="Adventures Of The Old West" UnitPrice="19.95">56775038991</Part>
         <Quantity>1.0</Quantity>
      </LineItem>
      <LineItem ItemNumber="2">
         <Part Description="Death Before Dishonor" UnitPrice="19.95">13131140798</Part>
         <Quantity>2.0</Quantity>
      </LineItem>
      <LineItem ItemNumber="3">
         <Part Description="Dragon Ball Z: The History of Trunks" UnitPrice="27.95">704400030048</Part>
         <Quantity>1.0</Quantity>
      </LineItem>
      <LineItem ItemNumber="4">
         <Part Description="The Cannonball Run" UnitPrice="19.95">26359060922</Part>
         <Quantity>2.0</Quantity>
      </LineItem>
      <LineItem ItemNumber="5">
         <Part Description="Mohammed: Messenger of God" UnitPrice="19.95">13131048292</Part>
         <Quantity>3.0</Quantity>
      </LineItem>
   </LineItems>
</PurchaseOrder>

